{
  "checksum": "f5bcc832000ce102a65686a5e1eee5731bbe42c88c0543d94f239458a644968b",
  "crates": {
    "az 1.2.1": {
      "name": "az",
      "version": "1.2.1",
      "repository": {
        "Http": {
          "url": "https://crates.io/api/v1/crates/az/1.2.1/download",
          "sha256": "7b7e4c2464d97fe331d41de9d5db0def0a96f4d823b8b32a2efd503578988973"
        }
      },
      "targets": [
        {
          "Library": {
            "crate_name": "az",
            "crate_root": "src/lib.rs",
            "srcs": [
              "**/*.rs"
            ]
          }
        },
        {
          "BuildScript": {
            "crate_name": "build_script_build",
            "crate_root": "build.rs",
            "srcs": [
              "**/*.rs"
            ]
          }
        }
      ],
      "library_target_name": "az",
      "common_attrs": {
        "compile_data_glob": [
          "**"
        ],
        "deps": {
          "common": [
            {
              "id": "az 1.2.1",
              "target": "build_script_build"
            }
          ],
          "selects": {}
        },
        "edition": "2018",
        "version": "1.2.1"
      },
      "build_script_attrs": {
        "data_glob": [
          "**"
        ]
      },
      "license": "MIT/Apache-2.0"
    },
    "gmp-mpfr-sys 1.6.1": {
      "name": "gmp-mpfr-sys",
      "version": "1.6.1",
      "repository": {
        "Http": {
          "url": "https://crates.io/api/v1/crates/gmp-mpfr-sys/1.6.1/download",
          "sha256": "19c5c67d8c29fe87e3266e691dd60948e6e4df4496c53355ef3551142945721b"
        }
      },
      "targets": [
        {
          "Library": {
            "crate_name": "gmp_mpfr_sys",
            "crate_root": "src/lib.rs",
            "srcs": [
              "**/*.rs"
            ]
          }
        },
        {
          "BuildScript": {
            "crate_name": "build_script_build",
            "crate_root": "build.rs",
            "srcs": [
              "**/*.rs"
            ]
          }
        }
      ],
      "library_target_name": "gmp_mpfr_sys",
      "common_attrs": {
        "compile_data_glob": [
          "**"
        ],
        "crate_features": {
          "common": [
            "mpc",
            "mpfr"
          ],
          "selects": {}
        },
        "deps": {
          "common": [
            {
              "id": "gmp-mpfr-sys 1.6.1",
              "target": "build_script_build"
            },
            {
              "id": "libc 0.2.147",
              "target": "libc"
            }
          ],
          "selects": {}
        },
        "edition": "2021",
        "version": "1.6.1"
      },
      "build_script_attrs": {
        "data_glob": [
          "**"
        ],
        "deps": {
          "common": [],
          "selects": {
            "cfg(target_os = \"windows\")": [
              {
                "id": "windows-sys 0.42.0",
                "target": "windows_sys"
              }
            ]
          }
        },
        "links": "gmp"
      },
      "license": "LGPL-3.0+"
    },
    "libc 0.2.147": {
      "name": "libc",
      "version": "0.2.147",
      "repository": {
        "Http": {
          "url": "https://crates.io/api/v1/crates/libc/0.2.147/download",
          "sha256": "b4668fb0ea861c1df094127ac5f1da3409a82116a4ba74fca2e58ef927159bb3"
        }
      },
      "targets": [
        {
          "Library": {
            "crate_name": "libc",
            "crate_root": "src/lib.rs",
            "srcs": [
              "**/*.rs"
            ]
          }
        },
        {
          "BuildScript": {
            "crate_name": "build_script_build",
            "crate_root": "build.rs",
            "srcs": [
              "**/*.rs"
            ]
          }
        }
      ],
      "library_target_name": "libc",
      "common_attrs": {
        "compile_data_glob": [
          "**"
        ],
        "deps": {
          "common": [
            {
              "id": "libc 0.2.147",
              "target": "build_script_build"
            }
          ],
          "selects": {}
        },
        "edition": "2015",
        "version": "0.2.147"
      },
      "build_script_attrs": {
        "data_glob": [
          "**"
        ]
      },
      "license": "MIT OR Apache-2.0"
    },
    "primes 0.1.0": {
      "name": "primes",
      "version": "0.1.0",
      "repository": null,
      "targets": [
        {
          "Library": {
            "crate_name": "primes",
            "crate_root": "src/lib.rs",
            "srcs": [
              "**/*.rs"
            ]
          }
        }
      ],
      "library_target_name": "primes",
      "common_attrs": {
        "compile_data_glob": [
          "**"
        ],
        "deps": {
          "common": [
            {
              "id": "rug 1.22.0",
              "target": "rug"
            }
          ],
          "selects": {}
        },
        "edition": "2021",
        "version": "0.1.0"
      },
      "license": null
    },
    "rug 1.22.0": {
      "name": "rug",
      "version": "1.22.0",
      "repository": {
        "Http": {
          "url": "https://crates.io/api/v1/crates/rug/1.22.0/download",
          "sha256": "5a118f8296241f6952511e8f9ab5b8a759c0d9ed902159b0aeed82d902e84ca6"
        }
      },
      "targets": [
        {
          "Library": {
            "crate_name": "rug",
            "crate_root": "src/lib.rs",
            "srcs": [
              "**/*.rs"
            ]
          }
        },
        {
          "BuildScript": {
            "crate_name": "build_script_build",
            "crate_root": "build.rs",
            "srcs": [
              "**/*.rs"
            ]
          }
        }
      ],
      "library_target_name": "rug",
      "common_attrs": {
        "compile_data_glob": [
          "**"
        ],
        "crate_features": {
          "common": [
            "complex",
            "default",
            "float",
            "gmp-mpfr-sys",
            "integer",
            "rand",
            "rational"
          ],
          "selects": {}
        },
        "deps": {
          "common": [
            {
              "id": "az 1.2.1",
              "target": "az"
            },
            {
              "id": "gmp-mpfr-sys 1.6.1",
              "target": "gmp_mpfr_sys"
            },
            {
              "id": "libc 0.2.147",
              "target": "libc"
            },
            {
              "id": "rug 1.22.0",
              "target": "build_script_build"
            }
          ],
          "selects": {}
        },
        "edition": "2021",
        "version": "1.22.0"
      },
      "build_script_attrs": {
        "data_glob": [
          "**"
        ],
        "link_deps": {
          "common": [
            {
              "id": "gmp-mpfr-sys 1.6.1",
              "target": "gmp_mpfr_sys"
            }
          ],
          "selects": {}
        }
      },
      "license": "LGPL-3.0+"
    },
    "windows-sys 0.42.0": {
      "name": "windows-sys",
      "version": "0.42.0",
      "repository": {
        "Http": {
          "url": "https://crates.io/api/v1/crates/windows-sys/0.42.0/download",
          "sha256": "5a3e1820f08b8513f676f7ab6c1f99ff312fb97b553d30ff4dd86f9f15728aa7"
        }
      },
      "targets": [
        {
          "Library": {
            "crate_name": "windows_sys",
            "crate_root": "src/lib.rs",
            "srcs": [
              "**/*.rs"
            ]
          }
        }
      ],
      "library_target_name": "windows_sys",
      "common_attrs": {
        "compile_data_glob": [
          "**"
        ],
        "deps": {
          "common": [],
          "selects": {
            "aarch64-pc-windows-gnullvm": [
              {
                "id": "windows_aarch64_gnullvm 0.42.2",
                "target": "windows_aarch64_gnullvm"
              }
            ],
            "aarch64-pc-windows-msvc": [
              {
                "id": "windows_aarch64_msvc 0.42.2",
                "target": "windows_aarch64_msvc"
              }
            ],
            "aarch64-uwp-windows-msvc": [
              {
                "id": "windows_aarch64_msvc 0.42.2",
                "target": "windows_aarch64_msvc"
              }
            ],
            "i686-pc-windows-gnu": [
              {
                "id": "windows_i686_gnu 0.42.2",
                "target": "windows_i686_gnu"
              }
            ],
            "i686-pc-windows-msvc": [
              {
                "id": "windows_i686_msvc 0.42.2",
                "target": "windows_i686_msvc"
              }
            ],
            "i686-uwp-windows-gnu": [
              {
                "id": "windows_i686_gnu 0.42.2",
                "target": "windows_i686_gnu"
              }
            ],
            "i686-uwp-windows-msvc": [
              {
                "id": "windows_i686_msvc 0.42.2",
                "target": "windows_i686_msvc"
              }
            ],
            "x86_64-pc-windows-gnu": [
              {
                "id": "windows_x86_64_gnu 0.42.2",
                "target": "windows_x86_64_gnu"
              }
            ],
            "x86_64-pc-windows-gnullvm": [
              {
                "id": "windows_x86_64_gnullvm 0.42.2",
                "target": "windows_x86_64_gnullvm"
              }
            ],
            "x86_64-pc-windows-msvc": [
              {
                "id": "windows_x86_64_msvc 0.42.2",
                "target": "windows_x86_64_msvc"
              }
            ],
            "x86_64-uwp-windows-gnu": [
              {
                "id": "windows_x86_64_gnu 0.42.2",
                "target": "windows_x86_64_gnu"
              }
            ],
            "x86_64-uwp-windows-msvc": [
              {
                "id": "windows_x86_64_msvc 0.42.2",
                "target": "windows_x86_64_msvc"
              }
            ]
          }
        },
        "edition": "2018",
        "version": "0.42.0"
      },
      "license": "MIT OR Apache-2.0"
    },
    "windows_aarch64_gnullvm 0.42.2": {
      "name": "windows_aarch64_gnullvm",
      "version": "0.42.2",
      "repository": {
        "Http": {
          "url": "https://crates.io/api/v1/crates/windows_aarch64_gnullvm/0.42.2/download",
          "sha256": "597a5118570b68bc08d8d59125332c54f1ba9d9adeedeef5b99b02ba2b0698f8"
        }
      },
      "targets": [
        {
          "Library": {
            "crate_name": "windows_aarch64_gnullvm",
            "crate_root": "src/lib.rs",
            "srcs": [
              "**/*.rs"
            ]
          }
        },
        {
          "BuildScript": {
            "crate_name": "build_script_build",
            "crate_root": "build.rs",
            "srcs": [
              "**/*.rs"
            ]
          }
        }
      ],
      "library_target_name": "windows_aarch64_gnullvm",
      "common_attrs": {
        "compile_data_glob": [
          "**"
        ],
        "deps": {
          "common": [
            {
              "id": "windows_aarch64_gnullvm 0.42.2",
              "target": "build_script_build"
            }
          ],
          "selects": {}
        },
        "edition": "2018",
        "version": "0.42.2"
      },
      "build_script_attrs": {
        "data_glob": [
          "**"
        ]
      },
      "license": "MIT OR Apache-2.0"
    },
    "windows_aarch64_msvc 0.42.2": {
      "name": "windows_aarch64_msvc",
      "version": "0.42.2",
      "repository": {
        "Http": {
          "url": "https://crates.io/api/v1/crates/windows_aarch64_msvc/0.42.2/download",
          "sha256": "e08e8864a60f06ef0d0ff4ba04124db8b0fb3be5776a5cd47641e942e58c4d43"
        }
      },
      "targets": [
        {
          "Library": {
            "crate_name": "windows_aarch64_msvc",
            "crate_root": "src/lib.rs",
            "srcs": [
              "**/*.rs"
            ]
          }
        },
        {
          "BuildScript": {
            "crate_name": "build_script_build",
            "crate_root": "build.rs",
            "srcs": [
              "**/*.rs"
            ]
          }
        }
      ],
      "library_target_name": "windows_aarch64_msvc",
      "common_attrs": {
        "compile_data_glob": [
          "**"
        ],
        "deps": {
          "common": [
            {
              "id": "windows_aarch64_msvc 0.42.2",
              "target": "build_script_build"
            }
          ],
          "selects": {}
        },
        "edition": "2018",
        "version": "0.42.2"
      },
      "build_script_attrs": {
        "data_glob": [
          "**"
        ]
      },
      "license": "MIT OR Apache-2.0"
    },
    "windows_i686_gnu 0.42.2": {
      "name": "windows_i686_gnu",
      "version": "0.42.2",
      "repository": {
        "Http": {
          "url": "https://crates.io/api/v1/crates/windows_i686_gnu/0.42.2/download",
          "sha256": "c61d927d8da41da96a81f029489353e68739737d3beca43145c8afec9a31a84f"
        }
      },
      "targets": [
        {
          "Library": {
            "crate_name": "windows_i686_gnu",
            "crate_root": "src/lib.rs",
            "srcs": [
              "**/*.rs"
            ]
          }
        },
        {
          "BuildScript": {
            "crate_name": "build_script_build",
            "crate_root": "build.rs",
            "srcs": [
              "**/*.rs"
            ]
          }
        }
      ],
      "library_target_name": "windows_i686_gnu",
      "common_attrs": {
        "compile_data_glob": [
          "**"
        ],
        "deps": {
          "common": [
            {
              "id": "windows_i686_gnu 0.42.2",
              "target": "build_script_build"
            }
          ],
          "selects": {}
        },
        "edition": "2018",
        "version": "0.42.2"
      },
      "build_script_attrs": {
        "data_glob": [
          "**"
        ]
      },
      "license": "MIT OR Apache-2.0"
    },
    "windows_i686_msvc 0.42.2": {
      "name": "windows_i686_msvc",
      "version": "0.42.2",
      "repository": {
        "Http": {
          "url": "https://crates.io/api/v1/crates/windows_i686_msvc/0.42.2/download",
          "sha256": "44d840b6ec649f480a41c8d80f9c65108b92d89345dd94027bfe06ac444d1060"
        }
      },
      "targets": [
        {
          "Library": {
            "crate_name": "windows_i686_msvc",
            "crate_root": "src/lib.rs",
            "srcs": [
              "**/*.rs"
            ]
          }
        },
        {
          "BuildScript": {
            "crate_name": "build_script_build",
            "crate_root": "build.rs",
            "srcs": [
              "**/*.rs"
            ]
          }
        }
      ],
      "library_target_name": "windows_i686_msvc",
      "common_attrs": {
        "compile_data_glob": [
          "**"
        ],
        "deps": {
          "common": [
            {
              "id": "windows_i686_msvc 0.42.2",
              "target": "build_script_build"
            }
          ],
          "selects": {}
        },
        "edition": "2018",
        "version": "0.42.2"
      },
      "build_script_attrs": {
        "data_glob": [
          "**"
        ]
      },
      "license": "MIT OR Apache-2.0"
    },
    "windows_x86_64_gnu 0.42.2": {
      "name": "windows_x86_64_gnu",
      "version": "0.42.2",
      "repository": {
        "Http": {
          "url": "https://crates.io/api/v1/crates/windows_x86_64_gnu/0.42.2/download",
          "sha256": "8de912b8b8feb55c064867cf047dda097f92d51efad5b491dfb98f6bbb70cb36"
        }
      },
      "targets": [
        {
          "Library": {
            "crate_name": "windows_x86_64_gnu",
            "crate_root": "src/lib.rs",
            "srcs": [
              "**/*.rs"
            ]
          }
        },
        {
          "BuildScript": {
            "crate_name": "build_script_build",
            "crate_root": "build.rs",
            "srcs": [
              "**/*.rs"
            ]
          }
        }
      ],
      "library_target_name": "windows_x86_64_gnu",
      "common_attrs": {
        "compile_data_glob": [
          "**"
        ],
        "deps": {
          "common": [
            {
              "id": "windows_x86_64_gnu 0.42.2",
              "target": "build_script_build"
            }
          ],
          "selects": {}
        },
        "edition": "2018",
        "version": "0.42.2"
      },
      "build_script_attrs": {
        "data_glob": [
          "**"
        ]
      },
      "license": "MIT OR Apache-2.0"
    },
    "windows_x86_64_gnullvm 0.42.2": {
      "name": "windows_x86_64_gnullvm",
      "version": "0.42.2",
      "repository": {
        "Http": {
          "url": "https://crates.io/api/v1/crates/windows_x86_64_gnullvm/0.42.2/download",
          "sha256": "26d41b46a36d453748aedef1486d5c7a85db22e56aff34643984ea85514e94a3"
        }
      },
      "targets": [
        {
          "Library": {
            "crate_name": "windows_x86_64_gnullvm",
            "crate_root": "src/lib.rs",
            "srcs": [
              "**/*.rs"
            ]
          }
        },
        {
          "BuildScript": {
            "crate_name": "build_script_build",
            "crate_root": "build.rs",
            "srcs": [
              "**/*.rs"
            ]
          }
        }
      ],
      "library_target_name": "windows_x86_64_gnullvm",
      "common_attrs": {
        "compile_data_glob": [
          "**"
        ],
        "deps": {
          "common": [
            {
              "id": "windows_x86_64_gnullvm 0.42.2",
              "target": "build_script_build"
            }
          ],
          "selects": {}
        },
        "edition": "2018",
        "version": "0.42.2"
      },
      "build_script_attrs": {
        "data_glob": [
          "**"
        ]
      },
      "license": "MIT OR Apache-2.0"
    },
    "windows_x86_64_msvc 0.42.2": {
      "name": "windows_x86_64_msvc",
      "version": "0.42.2",
      "repository": {
        "Http": {
          "url": "https://crates.io/api/v1/crates/windows_x86_64_msvc/0.42.2/download",
          "sha256": "9aec5da331524158c6d1a4ac0ab1541149c0b9505fde06423b02f5ef0106b9f0"
        }
      },
      "targets": [
        {
          "Library": {
            "crate_name": "windows_x86_64_msvc",
            "crate_root": "src/lib.rs",
            "srcs": [
              "**/*.rs"
            ]
          }
        },
        {
          "BuildScript": {
            "crate_name": "build_script_build",
            "crate_root": "build.rs",
            "srcs": [
              "**/*.rs"
            ]
          }
        }
      ],
      "library_target_name": "windows_x86_64_msvc",
      "common_attrs": {
        "compile_data_glob": [
          "**"
        ],
        "deps": {
          "common": [
            {
              "id": "windows_x86_64_msvc 0.42.2",
              "target": "build_script_build"
            }
          ],
          "selects": {}
        },
        "edition": "2018",
        "version": "0.42.2"
      },
      "build_script_attrs": {
        "data_glob": [
          "**"
        ]
      },
      "license": "MIT OR Apache-2.0"
    }
  },
  "binary_crates": [],
  "workspace_members": {
    "primes 0.1.0": ""
  },
  "conditions": {
    "aarch64-apple-darwin": [
      "aarch64-apple-darwin"
    ],
    "aarch64-apple-ios": [
      "aarch64-apple-ios"
    ],
    "aarch64-apple-ios-sim": [
      "aarch64-apple-ios-sim"
    ],
    "aarch64-fuchsia": [
      "aarch64-fuchsia"
    ],
    "aarch64-linux-android": [
      "aarch64-linux-android"
    ],
    "aarch64-pc-windows-gnullvm": [],
    "aarch64-pc-windows-msvc": [
      "aarch64-pc-windows-msvc"
    ],
    "aarch64-unknown-linux-gnu": [
      "aarch64-unknown-linux-gnu"
    ],
    "aarch64-uwp-windows-msvc": [],
    "arm-unknown-linux-gnueabi": [
      "arm-unknown-linux-gnueabi"
    ],
    "armv7-linux-androideabi": [
      "armv7-linux-androideabi"
    ],
    "armv7-unknown-linux-gnueabi": [
      "armv7-unknown-linux-gnueabi"
    ],
    "cfg(target_os = \"windows\")": [
      "aarch64-pc-windows-msvc",
      "i686-pc-windows-msvc",
      "x86_64-pc-windows-msvc"
    ],
    "i686-apple-darwin": [
      "i686-apple-darwin"
    ],
    "i686-linux-android": [
      "i686-linux-android"
    ],
    "i686-pc-windows-gnu": [],
    "i686-pc-windows-msvc": [
      "i686-pc-windows-msvc"
    ],
    "i686-unknown-freebsd": [
      "i686-unknown-freebsd"
    ],
    "i686-unknown-linux-gnu": [
      "i686-unknown-linux-gnu"
    ],
    "i686-uwp-windows-gnu": [],
    "i686-uwp-windows-msvc": [],
    "powerpc-unknown-linux-gnu": [
      "powerpc-unknown-linux-gnu"
    ],
    "riscv32imc-unknown-none-elf": [
      "riscv32imc-unknown-none-elf"
    ],
    "riscv64gc-unknown-none-elf": [
      "riscv64gc-unknown-none-elf"
    ],
    "s390x-unknown-linux-gnu": [
      "s390x-unknown-linux-gnu"
    ],
    "thumbv7em-none-eabi": [
      "thumbv7em-none-eabi"
    ],
    "thumbv8m.main-none-eabi": [
      "thumbv8m.main-none-eabi"
    ],
    "wasm32-unknown-unknown": [
      "wasm32-unknown-unknown"
    ],
    "wasm32-wasi": [
      "wasm32-wasi"
    ],
    "x86_64-apple-darwin": [
      "x86_64-apple-darwin"
    ],
    "x86_64-apple-ios": [
      "x86_64-apple-ios"
    ],
    "x86_64-fuchsia": [
      "x86_64-fuchsia"
    ],
    "x86_64-linux-android": [
      "x86_64-linux-android"
    ],
    "x86_64-pc-windows-gnu": [],
    "x86_64-pc-windows-gnullvm": [],
    "x86_64-pc-windows-msvc": [
      "x86_64-pc-windows-msvc"
    ],
    "x86_64-unknown-freebsd": [
      "x86_64-unknown-freebsd"
    ],
    "x86_64-unknown-linux-gnu": [
      "x86_64-unknown-linux-gnu"
    ],
    "x86_64-unknown-none": [
      "x86_64-unknown-none"
    ],
    "x86_64-uwp-windows-gnu": [],
    "x86_64-uwp-windows-msvc": []
  }
}
